hokohoko/Hokohoko.py
hokohoko/_period.py
hokohoko/_run.py
hokohoko/defaults.py
hokohoko/utils.py
hokohoko/entities/_Account.py
hokohoko/entities/_Assessor.py
hokohoko/entities/_Bar.py
hokohoko/entities/_Config.py
hokohoko/entities/_Data.py
hokohoko/entities/_Direction.py
hokohoko/entities/_Order.py
hokohoko/entities/_Position.py
hokohoko/entities/_Predictor.py
hokohoko/entities/_Status.py
hokohoko/entities/__init__.py
hokohoko/standard/_DoNothing.py
hokohoko/standard/_Logger.py
hokohoko/standard/_Npz.py
hokohoko/standard/__init__.py
hokohoko-0.1.0a1602446538.dist-info/METADATA
hokohoko-0.1.0a1602446538.dist-info/WHEEL
hokohoko-0.1.0a1602446538.dist-info/top_level.txt
hokohoko-0.1.0a1602446538.dist-info/RECORD
