Metadata-Version: 2.1
Name: hokohoko
Version: 0.1.0a1602446538
Summary: Provides a consistent interface to benchmark FOREX prediction projects.
Home-page: https://github.com/nc-bradley/Hokohoko
Author: Neil Bradley
Author-email: neil.bradley@bebecom.co.nz
License: UNKNOWN
Platform: UNKNOWN
Classifier: Programming Language :: Python :: 3
Classifier: License :: OSI Approved :: GNU General Public License v3 (GPLv3)
Classifier: Operating System :: OS Independent
Requires-Python: >=3.7
Requires-Dist: numpy
